yol_app/__init__.py
yol_app/server.py
yol_app/trace_logic.py
yol_app/trace_display/package-lock.json
yol_app/trace_display/package.json
yol_app/trace_display/public/favicon.ico
yol_app/trace_display/public/index.html
yol_app/trace_display/public/logo192.png
yol_app/trace_display/public/logo512.png
yol_app/trace_display/public/manifest.json
yol_app/trace_display/public/robots.txt
yol_app/trace_display/src/App.tsx
yol_app/trace_display/src/NeuralBridge.css
yol_app/trace_display/src/index.css
yol_app/trace_display/src/index.js
yol_app/trace_display/src/logo.svg
yol_app/trace_display/src/react-app-env.d.ts
yol_app/trace_display/src/components/CodeWindow.css
yol_app/trace_display/src/components/CodeWindow.tsx
yol_app/trace_display/src/components/Footer.css
yol_app/trace_display/src/components/Footer.tsx
yol_app/trace_display/src/components/Header.css
yol_app/trace_display/src/components/Header.tsx
yol_app/trace_display/src/components/InputOutputButton.css
yol_app/trace_display/src/components/InputOutputButton.tsx
yol_app/trace_display/src/components/InputOutputWindow.css
yol_app/trace_display/src/components/InputOutputWindow.tsx
yol_app/trace_display/src/components/NodeWindows.tsx
yol_app/trace_display/src/components/TraceGraph.tsx
yol_app/trace_display/src/components/TraceGraphContext.tsx
yol_app/trace_display/src/components/TraceGraphNode.css
yol_app/trace_display/src/components/TraceGraphNode.tsx
yol_app/trace_display/src/types/index.ts
yol_examples/__init__.py
yol_examples/callable_input_output.py
yol_examples/class_method.py
yol_examples/complex_school.py
yol_examples/dict_input_output.py
yol_examples/list_tester.py
yol_examples/lists_of_objects.py
yol_examples/long_input.py
yol_examples/many_function_calls.py
yol_examples/multi_thread.py
yol_examples/nested_list_of_objects.py
yol_examples/nested_objects.py
yol_examples/repeated_function.py
yol_examples/script.py
yol_examples/simple_object.py
yol_app-0.1.dist-info/LICENSE
yol_app-0.1.dist-info/METADATA
yol_app-0.1.dist-info/WHEEL
yol_app-0.1.dist-info/top_level.txt
yol_app-0.1.dist-info/RECORD
